hoboreader/__init__.py
hoboreader/hoboreader.py
hoboreader-0.0.2.dist-info/LICENSE
hoboreader-0.0.2.dist-info/METADATA
hoboreader-0.0.2.dist-info/WHEEL
hoboreader-0.0.2.dist-info/top_level.txt
hoboreader-0.0.2.dist-info/RECORD
