Metadata-Version: 2.1
Name: hoboreader
Version: 0.0.2
Summary: Python package for reading Onset Hobo sensor csv files
Home-page: https://github.com/building-energy/hoboreader
Author: Steven K Firth
Author-email: s.k.firth@lboro.ac.uk
License: UNKNOWN
Platform: UNKNOWN
Classifier: Programming Language :: Python :: 3
Classifier: License :: OSI Approved :: MIT License
Classifier: Operating System :: OS Independent
Requires-Python: >=3.6
